Metadata-Version: 1.0
Name: EIPy
Version: 0.3
Summary: Command-line EIP location tool
Home-page: http://github.com/halcyonlab/eipy
Author: Halcyon Lab
Author-email: UNKNOWN
License: UNKNOWN
Keywords: EIP offset exploit infosec pentest
Platform: UNKNOWN
